xtime/__init__.py
xtime/xtime.py
xtime-0.0.1.dist-info/LICENSE
xtime-0.0.1.dist-info/METADATA
xtime-0.0.1.dist-info/WHEEL
xtime-0.0.1.dist-info/top_level.txt
xtime-0.0.1.dist-info/RECORD
