Metadata-Version: 2.1
Name: xtime
Version: 0.0.1
Summary: xtime
Home-page: https://github.com/neoctobers/xtime
Author: @neoctobers
Author-email: neoctobers@gmail.com
License: UNKNOWN
Platform: UNKNOWN
Classifier: Programming Language :: Python :: 3
Classifier: License :: OSI Approved :: MIT License
Classifier: Operating System :: OS Independent
